HtmlTagNames/__init__.py
HtmlTagNames/html_tag_names.py
html_tag_names-0.1.1.dist-info/LICENSE
html_tag_names-0.1.1.dist-info/WHEEL
html_tag_names-0.1.1.dist-info/METADATA
html_tag_names-0.1.1.dist-info/RECORD
