Metadata-Version: 2.1
Name: html-tag-names
Version: 0.1.1
Summary: List of known HTML tag names
Home-page: https://github.com/Riverside-Healthcare/html-tag-names
License: MIT
Author: Christopher Pickering
Author-email: cpickering@rhc.net
Requires-Python: >=3.7,<4.0
Classifier: License :: OSI Approved :: MIT License
Classifier: Programming Language :: Python :: 3
Classifier: Programming Language :: Python :: 3.10
Classifier: Programming Language :: Python :: 3.7
Classifier: Programming Language :: Python :: 3.8
Classifier: Programming Language :: Python :: 3.9
Project-URL: Repository, https://github.com/Riverside-Healthcare/html-tag-names
